Coogle/__init__.py
Coogle/functions/__init__.py
Coogle/functions/exceptions.py
Coogle/functions/function01.py
Coogle/scripts/__init__.py
Coogle/scripts/script02.py
coogle-0.0.3.dist-info/METADATA
coogle-0.0.3.dist-info/WHEEL
coogle-0.0.3.dist-info/top_level.txt
coogle-0.0.3.dist-info/RECORD
